{
 "ordenPreguntas": [
  {
   "0": "optMultiple",
   "1": "optMultiple",
   "2": "optArrastrar",
   "3": "optArrastrar"
  }
 ],
 "preguntasModal1": [
  {
   "0": "Pregunta 1 opci\u00f3n m\u00faltiple",
   "1": "",
   "2": "A",
   "3": "Opci\u00f3n a",
   "4": "Opci\u00f3n b",
   "5": "Opci\u00f3n c",
   "6": "Opci\u00f3n d"
  },
  {
   "0": "Pregunta 1 opci\u00f3n m\u00faltiple",
   "1": "",
   "2": "C",
   "3": "Opci\u00f3n a",
   "4": "Opci\u00f3n b",
   "5": "Opci\u00f3n c",
   "6": "Opci\u00f3n d"
  }
 ],
 "preguntasModal2": [],
 "preguntasModal3": [],
 "preguntasModal4": [
  {
   "0": "Una los conceptos con sus definciones.",
   "1": "palabra 1**palabra 2",
   "2": "palabra 3**palabra 4"
  },
  {
   "0": "Una los conceptos con sus definciones.",
   "1": "palabra 1**palabra 2"
  }
 ]
}